{"movie_id": "tt0035885", "title": "Flesh and Fantasy", "introduction": "An anthology of three loosely connected occult tales, with ironic and romantic twists.", "runtime": "1h 34m", "runtimeSeconds": 5640, "rating": {"count": 1143, "star": 6.9}, "award": {"wins": 0, "nominations": 0}, "genre": ["Drama", "Fantasy", "Mystery", "Romance"], "releaseDate": "1943-10-29", "releaseLocation": "United States", "actors": ["Edward G. Robinson", "Charles Boyer", "Barbara Stanwyck"], "directors": ["Julien Duvivier"]}