{"movie_id": "tt0088247", "title": "The Terminator", "introduction": "A human soldier is sent from 2029 to 1984 to stop an almost indestructible cyborg killing machine, sent from the same year, which has been programmed to execute a young woman whose unborn son is the key to humanity's future salvation.", "runtime": "1h 47m", "runtimeSeconds": 6420, "rating": {"count": 920926, "star": 8.1}, "award": {"wins": 8, "nominations": 7}, "genre": ["Action", "Adventure", "Sci-Fi"], "releaseDate": "1984-10-26", "releaseLocation": "United States", "actors": ["Arnold Schwarzenegger", "Linda Hamilton", "Michael Biehn"], "directors": ["James Cameron"]}