{"movie_id": "tt0039806", "title": "The Sea of Grass", "introduction": "On America's frontier, a St. Louis woman marries a New Mexico cattleman who is seen as a tyrant by the locals.", "runtime": "2h 3m", "runtimeSeconds": 7380, "rating": {"count": 2434, "star": 6.3}, "award": {"wins": 0, "nominations": 0}, "genre": ["Drama", "Western"], "releaseDate": "1947-04-25", "releaseLocation": "United States", "actors": ["Katharine Hepburn", "Spencer Tracy", "Robert Walker"], "directors": ["Elia Kazan"]}