{"movie_id": "tt0069057", "title": "Pancho Villa", "introduction": "A double-cross in an arms deal prompts Mexican revolutionary Pancho Villa to raid a US Army weapons depot in Columbus, New Mexico.", "runtime": "1h 32m", "runtimeSeconds": 5520, "rating": {"count": 714, "star": 4.6}, "award": {"wins": 0, "nominations": 0}, "genre": ["Action", "Biography", "Comedy", "Drama", "Western"], "releaseDate": "1972-10-31", "releaseLocation": "West Germany", "actors": ["Telly Savalas", "Clint Walker", "Chuck Connors"], "directors": ["Eugenio Mart\u00edn"]}