{"movie_id": "tt0057115", "title": "The Great Escape", "introduction": "Allied prisoners of war plan for several hundred of their number to escape from a German camp during World War II.", "runtime": "2h 52m", "runtimeSeconds": 10320, "rating": {"count": 258040, "star": 8.2}, "award": {"wins": 3, "nominations": 11}, "genre": ["Adventure", "Drama", "Thriller", "War"], "releaseDate": "1963-07-04", "releaseLocation": "United States", "actors": ["Steve McQueen", "James Garner", "Richard Attenborough"], "directors": ["John Sturges"]}