{"movie_id": "tt0050083", "title": "12 Angry Men", "introduction": "The jury in a New York City murder trial is frustrated by a single member whose skeptical caution forces them to more carefully consider the evidence before jumping to a hasty verdict.", "runtime": "1h 36m", "runtimeSeconds": 5760, "rating": {"count": 860085, "star": 9}, "award": {"wins": 16, "nominations": 12}, "genre": ["Crime", "Drama"], "releaseDate": "1957-04-10", "releaseLocation": "United States", "actors": ["Henry Fonda", "Lee J. Cobb", "Martin Balsam"], "directors": ["Sidney Lumet"]}