{"movie_id": "tt0107290", "title": "Jurassic Park", "introduction": "A pragmatic paleontologist touring an almost complete theme park on an island in Central America is tasked with protecting a couple of kids after a power failure causes the park's cloned dinosaurs to run loose.", "runtime": "2h 7m", "runtimeSeconds": 7620, "rating": {"count": 1062345, "star": 8.2}, "award": {"wins": 44, "nominations": 27}, "genre": ["Action", "Adventure", "Sci-Fi", "Thriller"], "releaseDate": "1993-06-11", "releaseLocation": "United States", "actors": ["Sam Neill", "Laura Dern", "Jeff Goldblum"], "directors": ["Steven Spielberg"]}