{"movie_id": "tt0457430", "title": "Pan's Labyrinth", "introduction": "In the Falangist Spain of 1944, the bookish young stepdaughter of a sadistic army officer escapes into an eerie but captivating fantasy world.", "runtime": "1h 58m", "runtimeSeconds": 7080, "rating": {"count": 701172, "star": 8.2}, "award": {"wins": 109, "nominations": 115}, "genre": ["Drama", "Fantasy", "War"], "releaseDate": "2007-01-19", "releaseLocation": "United States", "actors": ["Ivana Baquero", "Ariadna Gil", "Sergi L\u00f3pez"], "directors": ["Guillermo del Toro"]}