{"movie_id": "tt1187064", "title": "Triangle", "introduction": "Five friends set sail and their yacht is overturned by a strange and sudden storm. A mysterious ship arrives to rescue them, and what happens next cannot be explained.", "runtime": "1h 39m", "runtimeSeconds": 5940, "rating": {"count": 129237, "star": 6.9}, "award": {"wins": 1, "nominations": 5}, "genre": ["Fantasy", "Mystery", "Sci-Fi", "Thriller"], "releaseDate": "2009-10-16", "releaseLocation": "United Kingdom", "actors": ["Melissa George", "Joshua McIvor", "Jack Taylor"], "directors": ["Christopher Smith"]}